dms_collector/__init__.py
dms_collector/__main__.py
dms_collector/dms.py
dms_collector-2.0.6.data/scripts/dms-collector
dms_collector-2.0.6.dist-info/METADATA
dms_collector-2.0.6.dist-info/WHEEL
dms_collector-2.0.6.dist-info/top_level.txt
dms_collector-2.0.6.dist-info/RECORD
