Metadata-Version: 2.1
Name: dms-collector
Version: 2.0.6
Summary: Oracle FMW DMS Spy collector utility
Home-page: UNKNOWN
Author: Tomas Vitvar
Author-email: tomas@vitvar.com
License: UNKNOWN
Platform: UNKNOWN
Classifier: Development Status :: 5 - Production/Stable
Classifier: Environment :: Console
Classifier: Intended Audience :: Developers
Classifier: Programming Language :: Python :: 3.5
Classifier: Programming Language :: Python :: 3.6
Classifier: Programming Language :: Python :: 3.7
Requires-Python: >=3.6.0
Requires-Dist: urllib3 (>=2.0.2)
Requires-Dist: requests (>=2.31.0)
Requires-Dist: setuptools-scm (>=6.3.2)
